pennylane_qsharp/__init__.py
pennylane_qsharp/_version.py
pennylane_qsharp/device.py
pennylane_qsharp/ops.py
pennylane_qsharp/quantum_simulator.py
PennyLane_qsharp-0.19.0.dist-info/LICENSE
PennyLane_qsharp-0.19.0.dist-info/METADATA
PennyLane_qsharp-0.19.0.dist-info/WHEEL
PennyLane_qsharp-0.19.0.dist-info/entry_points.txt
PennyLane_qsharp-0.19.0.dist-info/top_level.txt
PennyLane_qsharp-0.19.0.dist-info/RECORD
