Metadata-Version: 2.1
Name: PennyLane-qsharp
Version: 0.19.0
Summary: Microsoft Quantum Development Kit backend for PennyLane
Home-page: https://github.com/XanaduAI/pennylane-qsharp
Maintainer: Xanadu Inc.
Maintainer-email: josh@xanadu.ai
License: Apache License 2.0
Platform: UNKNOWN
Classifier: Development Status :: 4 - Beta
Classifier: Environment :: Console
Classifier: Intended Audience :: Science/Research
Classifier: License :: OSI Approved :: Apache Software License
Classifier: Natural Language :: English
Classifier: Operating System :: POSIX
Classifier: Operating System :: MacOS :: MacOS X
Classifier: Operating System :: POSIX :: Linux
Classifier: Operating System :: Microsoft :: Windows
Classifier: Programming Language :: Python
Classifier: Programming Language :: Python :: 3
Classifier: Programming Language :: Python :: 3.6
Classifier: Programming Language :: Python :: 3.7
Classifier: Programming Language :: Python :: 3 :: Only
Classifier: Topic :: Scientific/Engineering :: Physics
Provides: pennylane_qsharp
Requires-Dist: qsharp
Requires-Dist: pennylane (>=0.11)
